[
  {
    "district_id": "LK-71",
    "lg_id": "LG-71006",
    "ward_num": 0,
    "party": "FPF",
    "name": "Alakolangedara Ayesa Nilashani Jayasena"
  },
  {
    "district_id": "LK-71",
    "lg_id": "LG-71006",
    "ward_num": 0,
    "party": "FPF",
    "name": "Chanaka Sanjeewa Kariyawasam"
  },
  {
    "district_id": "LK-71",
    "lg_id": "LG-71006",
    "ward_num": 0,
    "party": "FPF",
    "name": "Kanishka Lakshan Wijesinghe"
  },
  {
    "district_id": "LK-71",
    "lg_id": "LG-71006",
    "ward_num": 0,
    "party": "FPF",
    "name": "Kumbalathara Arachchige Don Yasantha Nethmini"
  },
  {
    "district_id": "LK-71",
    "lg_id": "LG-71006",
    "ward_num": 0,
    "party": "FPF",
    "name": "Muthubandage Nirosha Priyangani Bandara"
  },
  {
    "district_id": "LK-71",
    "lg_id": "LG-71006",
    "ward_num": 0,
    "party": "FPF",
    "name": "Nishantha Wimal Gunadasa"
  },
  {
    "district_id": "LK-71",
    "lg_id": "LG-71006",
    "ward_num": 0,
    "party": "FPF",
    "name": "Pemananda Dissanayakalage Ineesha Rasadari Dissanayaka"
  },
  {
    "district_id": "LK-71",
    "lg_id": "LG-71006",
    "ward_num": 0,
    "party": "FPF",
    "name": "Seiyadu Ibrahim Mohomad Hakeem"
  },
  {
    "district_id": "LK-71",
    "lg_id": "LG-71006",
    "ward_num": 0,
    "party": "FPF",
    "name": "Swarnasiri Amanda Malkanthi"
  },
  {
    "district_id": "LK-71",
    "lg_id": "LG-71006",
    "ward_num": 0,
    "party": "FPF",
    "name": "Wijesundara Mudiyaselage Sanath Priayantha Wijesunadara"
  },
  {
    "district_id": "LK-71",
    "lg_id": "LG-71006",
    "ward_num": 0,
    "party": "JJB",
    "name": "Chandrasekara Mudiyanselage Rasika Shyamalee Chandrasekara"
  },
  {
    "district_id": "LK-71",
    "lg_id": "LG-71006",
    "ward_num": 0,
    "party": "JJB",
    "name": "Dharmapalage Bandula Senarathna"
  },
  {
    "district_id": "LK-71",
    "lg_id": "LG-71006",
    "ward_num": 0,
    "party": "JJB",
    "name": "Gunasenage Sarath Roopasinghe"
  },
  {
    "district_id": "LK-71",
    "lg_id": "LG-71006",
    "ward_num": 0,
    "party": "JJB",
    "name": "Herath Mudiyanselage Nayanananda Chandrasiri Herath"
  },
  {
    "district_id": "LK-71",
    "lg_id": "LG-71006",
    "ward_num": 0,
    "party": "JJB",
    "name": "Horathalge Chaya Dilrukshi"
  },
  {
    "district_id": "LK-71",
    "lg_id": "LG-71006",
    "ward_num": 0,
    "party": "JJB",
    "name": "Nihal Dissanayakage Shyamali Erandika Dissanayaka"
  },
  {
    "district_id": "LK-71",
    "lg_id": "LG-71006",
    "ward_num": 0,
    "party": "JJB",
    "name": "Podi Appuge Ashoka Jayarathna"
  },
  {
    "district_id": "LK-71",
    "lg_id": "LG-71006",
    "ward_num": 0,
    "party": "JJB",
    "name": "Sanjeewa Dhammika Dassanayaka"
  },
  {
    "district_id": "LK-71",
    "lg_id": "LG-71006",
    "ward_num": 0,
    "party": "JJB",
    "name": "Shalika Samanthi Sirisena"
  },
  {
    "district_id": "LK-71",
    "lg_id": "LG-71006",
    "ward_num": 0,
    "party": "JJB",
    "name": "Wijekoon Mudiyanselage Kusumalatha"
  },
  {
    "district_id": "LK-71",
    "lg_id": "LG-71006",
    "ward_num": 0,
    "party": "SJB",
    "name": "Jayathilakage Susanthi Anoma Jayathilaka"
  },
  {
    "district_id": "LK-71",
    "lg_id": "LG-71006",
    "ward_num": 0,
    "party": "SJB",
    "name": "Kiriyage Chandrasiri Dissanayaka"
  },
  {
    "district_id": "LK-71",
    "lg_id": "LG-71006",
    "ward_num": 0,
    "party": "SJB",
    "name": "Kuruppu Arachchilage Sasika Probodani"
  },
  {
    "district_id": "LK-71",
    "lg_id": "LG-71006",
    "ward_num": 0,
    "party": "SJB",
    "name": "Liyanage Dona Nisansala Samadhi Nanayakakara"
  },
  {
    "district_id": "LK-71",
    "lg_id": "LG-71006",
    "ward_num": 0,
    "party": "SJB",
    "name": "Naur Pichchey Naymdeen"
  },
  {
    "district_id": "LK-71",
    "lg_id": "LG-71006",
    "ward_num": 0,
    "party": "SJB",
    "name": "Segu Shafiyan"
  },
  {
    "district_id": "LK-71",
    "lg_id": "LG-71006",
    "ward_num": 0,
    "party": "SJB",
    "name": "Tikiri Appuge Sumanawathi"
  },
  {
    "district_id": "LK-71",
    "lg_id": "LG-71006",
    "ward_num": 0,
    "party": "SJB",
    "name": "Waranapalage Manori Warnasooriya"
  },
  {
    "district_id": "LK-71",
    "lg_id": "LG-71006",
    "ward_num": 0,
    "party": "SJB",
    "name": "Wijesinghage Chamodya Probodhani Wijesinghe"
  },
  {
    "district_id": "LK-71",
    "lg_id": "LG-71006",
    "ward_num": 0,
    "party": "SJB",
    "name": "Yatagama Lokuge Achira Shavinda"
  },
  {
    "district_id": "LK-71",
    "lg_id": "LG-71006",
    "ward_num": 0,
    "party": "SLFP",
    "name": "Bamunurathna Mudiyanselage Anula Kumari"
  },
  {
    "district_id": "LK-71",
    "lg_id": "LG-71006",
    "ward_num": 0,
    "party": "SLFP",
    "name": "Jayawickramage Chinthana Kumara"
  },
  {
    "district_id": "LK-71",
    "lg_id": "LG-71006",
    "ward_num": 0,
    "party": "SLFP",
    "name": "Mohammadu Kani Abdul Wahab"
  },
  {
    "district_id": "LK-71",
    "lg_id": "LG-71006",
    "ward_num": 0,
    "party": "SLFP",
    "name": "Mudali Hamige Dingiri Menika"
  },
  {
    "district_id": "LK-71",
    "lg_id": "LG-71006",
    "ward_num": 0,
    "party": "SLFP",
    "name": "Punchi Appuralage Sudarmalatha"
  },
  {
    "district_id": "LK-71",
    "lg_id": "LG-71006",
    "ward_num": 0,
    "party": "SLFP",
    "name": "Sabaragamu Koralalage Dona Dulika Nilanthi Gunathilaka"
  },
  {
    "district_id": "LK-71",
    "lg_id": "LG-71006",
    "ward_num": 0,
    "party": "SLFP",
    "name": "Sandhya Thilakarathna"
  },
  {
    "district_id": "LK-71",
    "lg_id": "LG-71006",
    "ward_num": 0,
    "party": "SLFP",
    "name": "Vipulasenage Thakshila Subhashani Vipulasena"
  },
  {
    "district_id": "LK-71",
    "lg_id": "LG-71006",
    "ward_num": 0,
    "party": "SLFP",
    "name": "Weerakkodi Arachchilage Don Thilini Lakmali Rohana"
  },
  {
    "district_id": "LK-71",
    "lg_id": "LG-71006",
    "ward_num": 0,
    "party": "SLFP",
    "name": "Weerasinghage Nalinda Weerasinghe"
  },
  {
    "district_id": "LK-71",
    "lg_id": "LG-71006",
    "ward_num": 0,
    "party": "SLMC",
    "name": "Abdul Majeedu Siththi Rejeena"
  },
  {
    "district_id": "LK-71",
    "lg_id": "LG-71006",
    "ward_num": 0,
    "party": "SLMC",
    "name": "Akbar Nasmiya"
  },
  {
    "district_id": "LK-71",
    "lg_id": "LG-71006",
    "ward_num": 0,
    "party": "SLMC",
    "name": "Daud Thajunnisa"
  },
  {
    "district_id": "LK-71",
    "lg_id": "LG-71006",
    "ward_num": 0,
    "party": "SLMC",
    "name": "Herath Bandage Sugathapala"
  },
  {
    "district_id": "LK-71",
    "lg_id": "LG-71006",
    "ward_num": 0,
    "party": "SLMC",
    "name": "Ismail Mohammad Tharukku"
  },
  {
    "district_id": "LK-71",
    "lg_id": "LG-71006",
    "ward_num": 0,
    "party": "SLMC",
    "name": "Mohammadu Kasim Sudahirdeen"
  },
  {
    "district_id": "LK-71",
    "lg_id": "LG-71006",
    "ward_num": 0,
    "party": "SLMC",
    "name": "Rasidu Roshan Hakthar"
  },
  {
    "district_id": "LK-71",
    "lg_id": "LG-71006",
    "ward_num": 0,
    "party": "SLMC",
    "name": "Risona Mohammadu Ripkan"
  },
  {
    "district_id": "LK-71",
    "lg_id": "LG-71006",
    "ward_num": 0,
    "party": "SLMC",
    "name": "Seinul Abdeen Pasmiya"
  },
  {
    "district_id": "LK-71",
    "lg_id": "LG-71006",
    "ward_num": 0,
    "party": "SLMC",
    "name": "Thuwan SharukIras Mohamad"
  },
  {
    "district_id": "LK-71",
    "lg_id": "LG-71006",
    "ward_num": 0,
    "party": "SLPP",
    "name": "Bandathe Rathnayake Mudiyanselage Janaka Saman Kumara"
  },
  {
    "district_id": "LK-71",
    "lg_id": "LG-71006",
    "ward_num": 0,
    "party": "SLPP",
    "name": "Gunapalage Abeysekara"
  },
  {
    "district_id": "LK-71",
    "lg_id": "LG-71006",
    "ward_num": 0,
    "party": "SLPP",
    "name": "Herath Bandage Sujith Kumar Herath"
  },
  {
    "district_id": "LK-71",
    "lg_id": "LG-71006",
    "ward_num": 0,
    "party": "SLPP",
    "name": "Herath Bandage Surasena Abeysekara"
  },
  {
    "district_id": "LK-71",
    "lg_id": "LG-71006",
    "ward_num": 0,
    "party": "SLPP",
    "name": "Herath Bandage Surasena Abeysekara"
  },
  {
    "district_id": "LK-71",
    "lg_id": "LG-71006",
    "ward_num": 0,
    "party": "SLPP",
    "name": "Herath Mudiyanselage Chamodhya Devmini Senadheera"
  },
  {
    "district_id": "LK-71",
    "lg_id": "LG-71006",
    "ward_num": 0,
    "party": "SLPP",
    "name": "Maliyadde Chandrima Kumari Jayarathna"
  },
  {
    "district_id": "LK-71",
    "lg_id": "LG-71006",
    "ward_num": 0,
    "party": "SLPP",
    "name": "Punchi Bandage Chalani Madhushika Disanayaka"
  },
  {
    "district_id": "LK-71",
    "lg_id": "LG-71006",
    "ward_num": 0,
    "party": "SLPP",
    "name": "Sachintha Priyabhashana Pathiraja"
  },
  {
    "district_id": "LK-71",
    "lg_id": "LG-71006",
    "ward_num": 0,
    "party": "SLPP",
    "name": "Swarna Ranasinghe Arachchi"
  },
  {
    "district_id": "LK-71",
    "lg_id": "LG-71006",
    "ward_num": 0,
    "party": "SLPP",
    "name": "Wijerathnage Priyanka Wijerathna"
  },
  {
    "district_id": "LK-71",
    "lg_id": "LG-71006",
    "ward_num": 0,
    "party": "UNP",
    "name": "Appuhamige Sarojani"
  },
  {
    "district_id": "LK-71",
    "lg_id": "LG-71006",
    "ward_num": 0,
    "party": "UNP",
    "name": "Galbokke Hevage Hemantha Rathnayaka"
  },
  {
    "district_id": "LK-71",
    "lg_id": "LG-71006",
    "ward_num": 0,
    "party": "UNP",
    "name": "Galbokke Hewage Sarojani Nelum Kumari"
  },
  {
    "district_id": "LK-71",
    "lg_id": "LG-71006",
    "ward_num": 0,
    "party": "UNP",
    "name": "Herath Mudiyanselage Nalina Udayana Herath"
  },
  {
    "district_id": "LK-71",
    "lg_id": "LG-71006",
    "ward_num": 0,
    "party": "UNP",
    "name": "Herath Mudiyanselage Nisansala Priyadarshini Herath"
  },
  {
    "district_id": "LK-71",
    "lg_id": "LG-71006",
    "ward_num": 0,
    "party": "UNP",
    "name": "Herath Mudiyanselage Suneth Kavinda Herath"
  },
  {
    "district_id": "LK-71",
    "lg_id": "LG-71006",
    "ward_num": 0,
    "party": "UNP",
    "name": "Pradeepa Nilmini Gunasekara"
  },
  {
    "district_id": "LK-71",
    "lg_id": "LG-71006",
    "ward_num": 0,
    "party": "UNP",
    "name": "Wijekoon Bandage Menaka Kamal Wijekoon"
  },
  {
    "district_id": "LK-71",
    "lg_id": "LG-71006",
    "ward_num": 0,
    "party": "UNP",
    "name": "Wijesundara Mudiyanselage Nihal Jayathilake"
  },
  {
    "district_id": "LK-71",
    "lg_id": "LG-71006",
    "ward_num": 0,
    "party": "UNP",
    "name": "Wijethungage Chandima Dilrukshi Wijebandara"
  },
  {
    "district_id": "LK-71",
    "lg_id": "LG-71006",
    "ward_num": 1,
    "party": "FPF",
    "name": "Wijesirige Shirani Wijekoon"
  },
  {
    "district_id": "LK-71",
    "lg_id": "LG-71006",
    "ward_num": 1,
    "party": "JJB",
    "name": "Wickramasinghe Arachchilage AsankaUdaya Kumara Rupasinghe"
  },
  {
    "district_id": "LK-71",
    "lg_id": "LG-71006",
    "ward_num": 1,
    "party": "SJB",
    "name": "Punchibandage Piyasiri Weerasinghe"
  },
  {
    "district_id": "LK-71",
    "lg_id": "LG-71006",
    "ward_num": 1,
    "party": "SLFP",
    "name": "Gunawardhanage Dharmapala"
  },
  {
    "district_id": "LK-71",
    "lg_id": "LG-71006",
    "ward_num": 1,
    "party": "SLMC",
    "name": "Mohammadu Sult?an Mohamad Najeed"
  },
  {
    "district_id": "LK-71",
    "lg_id": "LG-71006",
    "ward_num": 1,
    "party": "SLPP",
    "name": "Salibuge Thaibu"
  },
  {
    "district_id": "LK-71",
    "lg_id": "LG-71006",
    "ward_num": 1,
    "party": "UNP",
    "name": "Herath Mudiyanselage Prasanna Madu Kumara Herath"
  },
  {
    "district_id": "LK-71",
    "lg_id": "LG-71006",
    "ward_num": 2,
    "party": "FPF",
    "name": "Weerakkodi Pathirannehelage Sanjeewa Sarath Kumara"
  },
  {
    "district_id": "LK-71",
    "lg_id": "LG-71006",
    "ward_num": 2,
    "party": "JJB",
    "name": "Paththinige Jayarathna"
  },
  {
    "district_id": "LK-71",
    "lg_id": "LG-71006",
    "ward_num": 2,
    "party": "SJB",
    "name": "Lokugam Hewage Ananda Jayarathna"
  },
  {
    "district_id": "LK-71",
    "lg_id": "LG-71006",
    "ward_num": 2,
    "party": "SLFP",
    "name": "Gunarathnage Dinapala"
  },
  {
    "district_id": "LK-71",
    "lg_id": "LG-71006",
    "ward_num": 2,
    "party": "SLMC",
    "name": "Ikbal Mohamad Imran"
  },
  {
    "district_id": "LK-71",
    "lg_id": "LG-71006",
    "ward_num": 2,
    "party": "SLPP",
    "name": "Minikamgama Athige Ranil Madhawa Kamal Nilame"
  },
  {
    "district_id": "LK-71",
    "lg_id": "LG-71006",
    "ward_num": 2,
    "party": "UNP",
    "name": "Aloka Mudiyanselage Samanlatha"
  },
  {
    "district_id": "LK-71",
    "lg_id": "LG-71006",
    "ward_num": 3,
    "party": "FPF",
    "name": "Noor Mohomad Jabeer"
  },
  {
    "district_id": "LK-71",
    "lg_id": "LG-71006",
    "ward_num": 3,
    "party": "JJB",
    "name": "Ahamad Lebbe Jeinulabdeen"
  },
  {
    "district_id": "LK-71",
    "lg_id": "LG-71006",
    "ward_num": 3,
    "party": "SJB",
    "name": "Seynul Abdeen Ibrahim Sahib"
  },
  {
    "district_id": "LK-71",
    "lg_id": "LG-71006",
    "ward_num": 3,
    "party": "SLFP",
    "name": "Noor Mohamad Mohammadu Tharud"
  },
  {
    "district_id": "LK-71",
    "lg_id": "LG-71006",
    "ward_num": 3,
    "party": "SLMC",
    "name": "Ismail Mohamad Rifkan"
  },
  {
    "district_id": "LK-71",
    "lg_id": "LG-71006",
    "ward_num": 3,
    "party": "SLPP",
    "name": "Naiser Bistam Fathima Samrin"
  },
  {
    "district_id": "LK-71",
    "lg_id": "LG-71006",
    "ward_num": 3,
    "party": "UNP",
    "name": "Hetty Arachchige Rosan Danuska"
  },
  {
    "district_id": "LK-71",
    "lg_id": "LG-71006",
    "ward_num": 4,
    "party": "FPF",
    "name": "Mohommadu Ikbar Mohamad Inas"
  },
  {
    "district_id": "LK-71",
    "lg_id": "LG-71006",
    "ward_num": 4,
    "party": "JJB",
    "name": "Jayawardhanage Pemadasa"
  },
  {
    "district_id": "LK-71",
    "lg_id": "LG-71006",
    "ward_num": 4,
    "party": "SJB",
    "name": "Rathnayaka Mudiyanselage Chaminda Nalaka Saliyarathana"
  },
  {
    "district_id": "LK-71",
    "lg_id": "LG-71006",
    "ward_num": 4,
    "party": "SLFP",
    "name": "Thilakarathnage Asanka Lakmal"
  },
  {
    "district_id": "LK-71",
    "lg_id": "LG-71006",
    "ward_num": 4,
    "party": "SLMC",
    "name": "Ramlan Irshad"
  },
  {
    "district_id": "LK-71",
    "lg_id": "LG-71006",
    "ward_num": 4,
    "party": "SLPP",
    "name": "Mohammad Hanipa Ansar"
  },
  {
    "district_id": "LK-71",
    "lg_id": "LG-71006",
    "ward_num": 4,
    "party": "UNP",
    "name": "Herath Mudianselage Nandana Saranga Herath"
  },
  {
    "district_id": "LK-71",
    "lg_id": "LG-71006",
    "ward_num": 5,
    "party": "FPF",
    "name": "Sriyalatha Piyasena"
  },
  {
    "district_id": "LK-71",
    "lg_id": "LG-71006",
    "ward_num": 5,
    "party": "JJB",
    "name": "Appuhamige Ashoka Bandara Ralapanawa"
  },
  {
    "district_id": "LK-71",
    "lg_id": "LG-71006",
    "ward_num": 5,
    "party": "SJB",
    "name": "Ekanayakage Anil Buddhika Ekanayaka"
  },
  {
    "district_id": "LK-71",
    "lg_id": "LG-71006",
    "ward_num": 5,
    "party": "SLFP",
    "name": "Ganegala Walawwe Bandarage Kalyani Ganegala"
  },
  {
    "district_id": "LK-71",
    "lg_id": "LG-71006",
    "ward_num": 5,
    "party": "SLMC",
    "name": "Yunis Samsudeen"
  },
  {
    "district_id": "LK-71",
    "lg_id": "LG-71006",
    "ward_num": 5,
    "party": "SLPP",
    "name": "Dissanayake Mudiyanselage Herath Bandage Nishshanka Rajapaksa"
  },
  {
    "district_id": "LK-71",
    "lg_id": "LG-71006",
    "ward_num": 5,
    "party": "UNP",
    "name": "Renuka Gunasekara Velappilli"
  },
  {
    "district_id": "LK-71",
    "lg_id": "LG-71006",
    "ward_num": 6,
    "party": "FPF",
    "name": "Ranjith Dissanayaka"
  },
  {
    "district_id": "LK-71",
    "lg_id": "LG-71006",
    "ward_num": 6,
    "party": "JJB",
    "name": "Dassanayakage Ashen Prasad Dassanayaka"
  },
  {
    "district_id": "LK-71",
    "lg_id": "LG-71006",
    "ward_num": 6,
    "party": "SJB",
    "name": "Nalin Sisira Kumara Jayawardhana"
  },
  {
    "district_id": "LK-71",
    "lg_id": "LG-71006",
    "ward_num": 6,
    "party": "SLFP",
    "name": "Kapuralage Senevirathna"
  },
  {
    "district_id": "LK-71",
    "lg_id": "LG-71006",
    "ward_num": 6,
    "party": "SLMC",
    "name": "V.H.M. Nissanga Bandara"
  },
  {
    "district_id": "LK-71",
    "lg_id": "LG-71006",
    "ward_num": 6,
    "party": "SLPP",
    "name": "Lalith Aruna Shantha Thilakaratna Koralage"
  },
  {
    "district_id": "LK-71",
    "lg_id": "LG-71006",
    "ward_num": 6,
    "party": "UNP",
    "name": "Herath Mudiyanselage Lakshika Madhuwanthi"
  },
  {
    "district_id": "LK-71",
    "lg_id": "LG-71006",
    "ward_num": 7,
    "party": "FPF",
    "name": "Piyasirige Nishan Chathuranga Piyasiri"
  },
  {
    "district_id": "LK-71",
    "lg_id": "LG-71006",
    "ward_num": 7,
    "party": "JJB",
    "name": "Karunarathnage Dinesh Kumara Karunarathna"
  },
  {
    "district_id": "LK-71",
    "lg_id": "LG-71006",
    "ward_num": 7,
    "party": "SJB",
    "name": "Punchibandage Piyasiri Rathnayaka"
  },
  {
    "district_id": "LK-71",
    "lg_id": "LG-71006",
    "ward_num": 7,
    "party": "SLFP",
    "name": "Chandrasekara Mudiyanselage Dhananjana Lakmal"
  },
  {
    "district_id": "LK-71",
    "lg_id": "LG-71006",
    "ward_num": 7,
    "party": "SLMC",
    "name": "Kirihamige Ramyalatha"
  },
  {
    "district_id": "LK-71",
    "lg_id": "LG-71006",
    "ward_num": 7,
    "party": "SLPP",
    "name": "Disanayaka Mudiyanselage Saman Kumara Disanayaka"
  },
  {
    "district_id": "LK-71",
    "lg_id": "LG-71006",
    "ward_num": 7,
    "party": "UNP",
    "name": "Adhikarige Don Chaminda Piyathilaka"
  },
  {
    "district_id": "LK-71",
    "lg_id": "LG-71006",
    "ward_num": 8,
    "party": "FPF",
    "name": "Rannaidege Rumesh Sadaruwan"
  },
  {
    "district_id": "LK-71",
    "lg_id": "LG-71006",
    "ward_num": 8,
    "party": "JJB",
    "name": "Upali Premathilaka Dissanayaka"
  },
  {
    "district_id": "LK-71",
    "lg_id": "LG-71006",
    "ward_num": 8,
    "party": "SJB",
    "name": "Shyalika Maduranga Subhasinghe"
  },
  {
    "district_id": "LK-71",
    "lg_id": "LG-71006",
    "ward_num": 8,
    "party": "SLFP",
    "name": "Koswaththe Gedara Ajith Koswaththa"
  },
  {
    "district_id": "LK-71",
    "lg_id": "LG-71006",
    "ward_num": 8,
    "party": "SLMC",
    "name": "Seeni Mohamad Mohamad Nafeer"
  },
  {
    "district_id": "LK-71",
    "lg_id": "LG-71006",
    "ward_num": 8,
    "party": "SLPP",
    "name": "Samarakoon Mudiyanselage Asoka Sumanasiri Bandara"
  },
  {
    "district_id": "LK-71",
    "lg_id": "LG-71006",
    "ward_num": 8,
    "party": "UNP",
    "name": "Sakunthala Priyadarshini Rathnayaka"
  },
  {
    "district_id": "LK-71",
    "lg_id": "LG-71006",
    "ward_num": 9,
    "party": "FPF",
    "name": "Disanayaka Mudiyanselage Shyamal Gayan"
  },
  {
    "district_id": "LK-71",
    "lg_id": "LG-71006",
    "ward_num": 9,
    "party": "JJB",
    "name": "Piyadasa Thenna koonlage Anuradha Kumarasinghe"
  },
  {
    "district_id": "LK-71",
    "lg_id": "LG-71006",
    "ward_num": 9,
    "party": "SJB",
    "name": "Appuhamige Weerasena Disanayaka"
  },
  {
    "district_id": "LK-71",
    "lg_id": "LG-71006",
    "ward_num": 9,
    "party": "SLFP",
    "name": "Gunarathnage Chamara Pradeep Gunaratne"
  },
  {
    "district_id": "LK-71",
    "lg_id": "LG-71006",
    "ward_num": 9,
    "party": "SLMC",
    "name": "Napeer Mohamad Naseer"
  },
  {
    "district_id": "LK-71",
    "lg_id": "LG-71006",
    "ward_num": 9,
    "party": "SLPP",
    "name": "Sugathapalage Nishantha Kumara Subhasingha"
  },
  {
    "district_id": "LK-71",
    "lg_id": "LG-71006",
    "ward_num": 9,
    "party": "UNP",
    "name": "Rathnayaka Mudiyanselage Chandani Madhushani Wijesinghe"
  },
  {
    "district_id": "LK-71",
    "lg_id": "LG-71006",
    "ward_num": 10,
    "party": "FPF",
    "name": "Ranasinghe Arachchilage Ranjith Kumarasingha"
  },
  {
    "district_id": "LK-71",
    "lg_id": "LG-71006",
    "ward_num": 10,
    "party": "JJB",
    "name": "Wasala Mudiyanselage Susantha Kumara Nawarathna"
  },
  {
    "district_id": "LK-71",
    "lg_id": "LG-71006",
    "ward_num": 10,
    "party": "SJB",
    "name": "Dhammika Doltan Abeywickrama"
  },
  {
    "district_id": "LK-71",
    "lg_id": "LG-71006",
    "ward_num": 10,
    "party": "SLFP",
    "name": "Udahagedara Chandana Prabhath Rajapaksha"
  },
  {
    "district_id": "LK-71",
    "lg_id": "LG-71006",
    "ward_num": 10,
    "party": "SLMC",
    "name": "Rifkan Imran Naseem"
  },
  {
    "district_id": "LK-71",
    "lg_id": "LG-71006",
    "ward_num": 10,
    "party": "SLPP",
    "name": "Sampath Kumar Allis Weerasinghe"
  },
  {
    "district_id": "LK-71",
    "lg_id": "LG-71006",
    "ward_num": 10,
    "party": "UNP",
    "name": "Herath Mudiyanselage Chanaka Sadamal Herath"
  },
  {
    "district_id": "LK-71",
    "lg_id": "LG-71006",
    "ward_num": 11,
    "party": "FPF",
    "name": "Muhamdiramge Piyantha Wijerathna"
  },
  {
    "district_id": "LK-71",
    "lg_id": "LG-71006",
    "ward_num": 11,
    "party": "JJB",
    "name": "Wanigasekarage Rohana Gunasekara"
  },
  {
    "district_id": "LK-71",
    "lg_id": "LG-71006",
    "ward_num": 11,
    "party": "SJB",
    "name": "Basnayaka Mudiyanselage Manel Kumari Basnayaka"
  },
  {
    "district_id": "LK-71",
    "lg_id": "LG-71006",
    "ward_num": 11,
    "party": "SLFP",
    "name": "Loku Dombawalage Nalika Thushari"
  },
  {
    "district_id": "LK-71",
    "lg_id": "LG-71006",
    "ward_num": 11,
    "party": "SLMC",
    "name": "Mohammadu Saburdeen Shakir Hasan"
  },
  {
    "district_id": "LK-71",
    "lg_id": "LG-71006",
    "ward_num": 11,
    "party": "SLPP",
    "name": "Rathnayake Mudiyanselage Padmasiri Dissanayaka"
  },
  {
    "district_id": "LK-71",
    "lg_id": "LG-71006",
    "ward_num": 11,
    "party": "UNP",
    "name": "Herath Mudiyanselage Gunathilaka"
  }
]