[
  {
    "district_id": "LK-81",
    "lg_id": "LG-81006",
    "ward_num": 0,
    "party": "CWC(",
    "name": "Arumugam Udearakumar"
  },
  {
    "district_id": "LK-81",
    "lg_id": "LG-81006",
    "ward_num": 0,
    "party": "CWC(",
    "name": "Chandrakumar Nishanthini"
  },
  {
    "district_id": "LK-81",
    "lg_id": "LG-81006",
    "ward_num": 0,
    "party": "CWC(",
    "name": "Francis Demels"
  },
  {
    "district_id": "LK-81",
    "lg_id": "LG-81006",
    "ward_num": 0,
    "party": "CWC(",
    "name": "Kandan Sridharan"
  },
  {
    "district_id": "LK-81",
    "lg_id": "LG-81006",
    "ward_num": 0,
    "party": "CWC(",
    "name": "Ponnaiya Pushparani"
  },
  {
    "district_id": "LK-81",
    "lg_id": "LG-81006",
    "ward_num": 0,
    "party": "CWC(",
    "name": "Ponnaiya Thilani"
  },
  {
    "district_id": "LK-81",
    "lg_id": "LG-81006",
    "ward_num": 0,
    "party": "CWC(",
    "name": "Rajagobal Saridha"
  },
  {
    "district_id": "LK-81",
    "lg_id": "LG-81006",
    "ward_num": 0,
    "party": "CWC(",
    "name": "Rajendran Srikanth"
  },
  {
    "district_id": "LK-81",
    "lg_id": "LG-81006",
    "ward_num": 0,
    "party": "CWC(",
    "name": "Selvaraj Niranjan"
  },
  {
    "district_id": "LK-81",
    "lg_id": "LG-81006",
    "ward_num": 0,
    "party": "CWC(",
    "name": "Selvaraja Theleeba"
  },
  {
    "district_id": "LK-81",
    "lg_id": "LG-81006",
    "ward_num": 0,
    "party": "CWC(",
    "name": "Thangaraj Raguman"
  },
  {
    "district_id": "LK-81",
    "lg_id": "LG-81006",
    "ward_num": 0,
    "party": "FPF",
    "name": "Hennayaka Mudiyanselage Dhanushka Kelum Bandara"
  },
  {
    "district_id": "LK-81",
    "lg_id": "LG-81006",
    "ward_num": 0,
    "party": "FPF",
    "name": "Kodithuwakku Arachchilage Swarnalatha"
  },
  {
    "district_id": "LK-81",
    "lg_id": "LG-81006",
    "ward_num": 0,
    "party": "FPF",
    "name": "Mahanama Weerasekara Dayawathi"
  },
  {
    "district_id": "LK-81",
    "lg_id": "LG-81006",
    "ward_num": 0,
    "party": "FPF",
    "name": "Ramalingam Kalei Kumar"
  },
  {
    "district_id": "LK-81",
    "lg_id": "LG-81006",
    "ward_num": 0,
    "party": "FPF",
    "name": "Rathgama Guruge Ramyalatha de Silva"
  },
  {
    "district_id": "LK-81",
    "lg_id": "LG-81006",
    "ward_num": 0,
    "party": "FPF",
    "name": "Thennakoon Mudiyanselage Nalani"
  },
  {
    "district_id": "LK-81",
    "lg_id": "LG-81006",
    "ward_num": 0,
    "party": "FPF",
    "name": "Thennakoon Mudiyanselage Udeni Yasarathna"
  },
  {
    "district_id": "LK-81",
    "lg_id": "LG-81006",
    "ward_num": 0,
    "party": "FPF",
    "name": "Wanasingha Mudiyanselage Ghanawathi"
  },
  {
    "district_id": "LK-81",
    "lg_id": "LG-81006",
    "ward_num": 0,
    "party": "FPF",
    "name": "Weerasingha Mudiyanselage Upali Gunasekara"
  },
  {
    "district_id": "LK-81",
    "lg_id": "LG-81006",
    "ward_num": 0,
    "party": "FPF",
    "name": "Wissundara Mudiyanselage Devika Malkanthi"
  },
  {
    "district_id": "LK-81",
    "lg_id": "LG-81006",
    "ward_num": 0,
    "party": "FPF",
    "name": "Wissundara Mudiyanselage Sarath Nishshanka"
  },
  {
    "district_id": "LK-81",
    "lg_id": "LG-81006",
    "ward_num": 0,
    "party": "IG1",
    "name": "Abdul Latheef Elam Selvi"
  },
  {
    "district_id": "LK-81",
    "lg_id": "LG-81006",
    "ward_num": 0,
    "party": "IG1",
    "name": "Bogahawaththe Gedara Charuka Predeep Bogahawaththa"
  },
  {
    "district_id": "LK-81",
    "lg_id": "LG-81006",
    "ward_num": 0,
    "party": "IG1",
    "name": "Dissanayaka Mudiyanselage Anurapala"
  },
  {
    "district_id": "LK-81",
    "lg_id": "LG-81006",
    "ward_num": 0,
    "party": "IG1",
    "name": "Egodawaththe Ralalage Senadeera Bandara"
  },
  {
    "district_id": "LK-81",
    "lg_id": "LG-81006",
    "ward_num": 0,
    "party": "IG1",
    "name": "Ganegoda Gamage Harasha Ramani"
  },
  {
    "district_id": "LK-81",
    "lg_id": "LG-81006",
    "ward_num": 0,
    "party": "IG1",
    "name": "Piawelagama Nandathissa Thero"
  },
  {
    "district_id": "LK-81",
    "lg_id": "LG-81006",
    "ward_num": 0,
    "party": "IG1",
    "name": "Rathnayaka Mudiyanselage Arunalatha"
  },
  {
    "district_id": "LK-81",
    "lg_id": "LG-81006",
    "ward_num": 0,
    "party": "IG1",
    "name": "Raveendran Darshani"
  },
  {
    "district_id": "LK-81",
    "lg_id": "LG-81006",
    "ward_num": 0,
    "party": "IG1",
    "name": "Sahul Hameed Pathima Wasima"
  },
  {
    "district_id": "LK-81",
    "lg_id": "LG-81006",
    "ward_num": 0,
    "party": "IG1",
    "name": "Velu Thamilwanan"
  },
  {
    "district_id": "LK-81",
    "lg_id": "LG-81006",
    "ward_num": 0,
    "party": "IG1",
    "name": "Wickramasingha Mudiyanselage Janaka Rukman Wickramasingha"
  },
  {
    "district_id": "LK-81",
    "lg_id": "LG-81006",
    "ward_num": 0,
    "party": "JJB",
    "name": "A. Palitha Liwera"
  },
  {
    "district_id": "LK-81",
    "lg_id": "LG-81006",
    "ward_num": 0,
    "party": "JJB",
    "name": "D.M. Geethanjali Sandamalika Dissanayaka"
  },
  {
    "district_id": "LK-81",
    "lg_id": "LG-81006",
    "ward_num": 0,
    "party": "JJB",
    "name": "D.P. Wasanthi Pathmakumari"
  },
  {
    "district_id": "LK-81",
    "lg_id": "LG-81006",
    "ward_num": 0,
    "party": "JJB",
    "name": "H.M. Udeshika Priyadarshani Herath"
  },
  {
    "district_id": "LK-81",
    "lg_id": "LG-81006",
    "ward_num": 0,
    "party": "JJB",
    "name": "K.P.R. Piyasena"
  },
  {
    "district_id": "LK-81",
    "lg_id": "LG-81006",
    "ward_num": 0,
    "party": "JJB",
    "name": "R.M. Chaminda Thilanka Amarathunga"
  },
  {
    "district_id": "LK-81",
    "lg_id": "LG-81006",
    "ward_num": 0,
    "party": "JJB",
    "name": "R.M. Sugathapala"
  },
  {
    "district_id": "LK-81",
    "lg_id": "LG-81006",
    "ward_num": 0,
    "party": "JJB",
    "name": "R.P. Janith Sandakelum Kulasooriya"
  },
  {
    "district_id": "LK-81",
    "lg_id": "LG-81006",
    "ward_num": 0,
    "party": "JJB",
    "name": "S.M. Sevmini Chathurangani Sooriyarathna"
  },
  {
    "district_id": "LK-81",
    "lg_id": "LG-81006",
    "ward_num": 0,
    "party": "JJB",
    "name": "Sithambaram Parameswari"
  },
  {
    "district_id": "LK-81",
    "lg_id": "LG-81006",
    "ward_num": 0,
    "party": "JJB",
    "name": "W.M. Wijedasa"
  },
  {
    "district_id": "LK-81",
    "lg_id": "LG-81006",
    "ward_num": 0,
    "party": "NDF",
    "name": "Ghanaprakasam Selvamalar"
  },
  {
    "district_id": "LK-81",
    "lg_id": "LG-81006",
    "ward_num": 0,
    "party": "NDF",
    "name": "Kadirawel Mahalingam"
  },
  {
    "district_id": "LK-81",
    "lg_id": "LG-81006",
    "ward_num": 0,
    "party": "NDF",
    "name": "Kadireshan Chithra"
  },
  {
    "district_id": "LK-81",
    "lg_id": "LG-81006",
    "ward_num": 0,
    "party": "NDF",
    "name": "Maialagu Panirselvam"
  },
  {
    "district_id": "LK-81",
    "lg_id": "LG-81006",
    "ward_num": 0,
    "party": "NDF",
    "name": "Mariyadas Thamilwani"
  },
  {
    "district_id": "LK-81",
    "lg_id": "LG-81006",
    "ward_num": 0,
    "party": "NDF",
    "name": "Mookaiya Kanagamma"
  },
  {
    "district_id": "LK-81",
    "lg_id": "LG-81006",
    "ward_num": 0,
    "party": "NDF",
    "name": "Partheeban Mahadewan"
  },
  {
    "district_id": "LK-81",
    "lg_id": "LG-81006",
    "ward_num": 0,
    "party": "NDF",
    "name": "Pichchamuththu Nisanthi"
  },
  {
    "district_id": "LK-81",
    "lg_id": "LG-81006",
    "ward_num": 0,
    "party": "NDF",
    "name": "Raman Wijayendran"
  },
  {
    "district_id": "LK-81",
    "lg_id": "LG-81006",
    "ward_num": 0,
    "party": "NDF",
    "name": "Sinnayya Ramadas"
  },
  {
    "district_id": "LK-81",
    "lg_id": "LG-81006",
    "ward_num": 0,
    "party": "NDF",
    "name": "Subramaniyam Kukan"
  },
  {
    "district_id": "LK-81",
    "lg_id": "LG-81006",
    "ward_num": 0,
    "party": "SJB",
    "name": "Adagalagedara Diluka Chathurani Weerathunga"
  },
  {
    "district_id": "LK-81",
    "lg_id": "LG-81006",
    "ward_num": 0,
    "party": "SJB",
    "name": "Appuhannadige Amilaruwan Sanjiwana"
  },
  {
    "district_id": "LK-81",
    "lg_id": "LG-81006",
    "ward_num": 0,
    "party": "SJB",
    "name": "Balasundaram Pushparaj"
  },
  {
    "district_id": "LK-81",
    "lg_id": "LG-81006",
    "ward_num": 0,
    "party": "SJB",
    "name": "Hewa Ponsekage Godvin Gunawardhana Ponseka"
  },
  {
    "district_id": "LK-81",
    "lg_id": "LG-81006",
    "ward_num": 0,
    "party": "SJB",
    "name": "Koggala Liyana Patabadige Gnanawathi"
  },
  {
    "district_id": "LK-81",
    "lg_id": "LG-81006",
    "ward_num": 0,
    "party": "SJB",
    "name": "Kumarawel Thamil Chelvam"
  },
  {
    "district_id": "LK-81",
    "lg_id": "LG-81006",
    "ward_num": 0,
    "party": "SJB",
    "name": "Mahawaduge Padmalatha"
  },
  {
    "district_id": "LK-81",
    "lg_id": "LG-81006",
    "ward_num": 0,
    "party": "SJB",
    "name": "Rathnayaka Mudiyanselage Ghanathilaka"
  },
  {
    "district_id": "LK-81",
    "lg_id": "LG-81006",
    "ward_num": 0,
    "party": "SJB",
    "name": "Rathnayaka Mudiyanselage Mithrananda Udaya Kumara Rathnayaka"
  },
  {
    "district_id": "LK-81",
    "lg_id": "LG-81006",
    "ward_num": 0,
    "party": "SJB",
    "name": "Weerasiri Ganegoda Nalika Geethanjali Samarajeewa"
  },
  {
    "district_id": "LK-81",
    "lg_id": "LG-81006",
    "ward_num": 0,
    "party": "SJB",
    "name": "Wijesingha Mudiyanselage Chandrawathi"
  },
  {
    "district_id": "LK-81",
    "lg_id": "LG-81006",
    "ward_num": 0,
    "party": "SLPP",
    "name": "Dharmalingam Kumarawelu"
  },
  {
    "district_id": "LK-81",
    "lg_id": "LG-81006",
    "ward_num": 0,
    "party": "SLPP",
    "name": "Dissanayaka Mudiyanselage Dewasiri"
  },
  {
    "district_id": "LK-81",
    "lg_id": "LG-81006",
    "ward_num": 0,
    "party": "SLPP",
    "name": "Dissanayaka Mudiyanselage Gamini Dissanayaka"
  },
  {
    "district_id": "LK-81",
    "lg_id": "LG-81006",
    "ward_num": 0,
    "party": "SLPP",
    "name": "Dissanayaka Mudiyanselage Indika Hemantha Dissanayaka"
  },
  {
    "district_id": "LK-81",
    "lg_id": "LG-81006",
    "ward_num": 0,
    "party": "SLPP",
    "name": "Kahakachchi Patabadige Irangani"
  },
  {
    "district_id": "LK-81",
    "lg_id": "LG-81006",
    "ward_num": 0,
    "party": "SLPP",
    "name": "Koralage Ghanawathi Silva"
  },
  {
    "district_id": "LK-81",
    "lg_id": "LG-81006",
    "ward_num": 0,
    "party": "SLPP",
    "name": "Manikka Badathurage Kusumawathi"
  },
  {
    "district_id": "LK-81",
    "lg_id": "LG-81006",
    "ward_num": 0,
    "party": "SLPP",
    "name": "Manikka Badathuruge Seetha Irangani"
  },
  {
    "district_id": "LK-81",
    "lg_id": "LG-81006",
    "ward_num": 0,
    "party": "SLPP",
    "name": "Pallewelage Dharmasiri Gamage"
  },
  {
    "district_id": "LK-81",
    "lg_id": "LG-81006",
    "ward_num": 0,
    "party": "SLPP",
    "name": "Polwaththe Giganage Ranjith Sunil De Silva"
  },
  {
    "district_id": "LK-81",
    "lg_id": "LG-81006",
    "ward_num": 0,
    "party": "SLPP",
    "name": "Ranhoti Bandaralage Oshadhi Madhumali"
  },
  {
    "district_id": "LK-81",
    "lg_id": "LG-81006",
    "ward_num": 0,
    "party": "UNP",
    "name": "Aththanayaka Mudiyanselage Navodya Irudika Aththanayaka"
  },
  {
    "district_id": "LK-81",
    "lg_id": "LG-81006",
    "ward_num": 0,
    "party": "UNP",
    "name": "Dissanayaka Mudiyanselage Binusika Prasansa Poojani Wijerathna"
  },
  {
    "district_id": "LK-81",
    "lg_id": "LG-81006",
    "ward_num": 0,
    "party": "UNP",
    "name": "Dissanayaka Mudiyanselage Dharmakeerthi"
  },
  {
    "district_id": "LK-81",
    "lg_id": "LG-81006",
    "ward_num": 0,
    "party": "UNP",
    "name": "Kalimuththu Subendran"
  },
  {
    "district_id": "LK-81",
    "lg_id": "LG-81006",
    "ward_num": 0,
    "party": "UNP",
    "name": "Mohomad Lafeer Mohomad Lareef"
  },
  {
    "district_id": "LK-81",
    "lg_id": "LG-81006",
    "ward_num": 0,
    "party": "UNP",
    "name": "Palanda Hewage Gangananda Bandara"
  },
  {
    "district_id": "LK-81",
    "lg_id": "LG-81006",
    "ward_num": 0,
    "party": "UNP",
    "name": "Rajapaksha Mudiyanselage Nandani"
  },
  {
    "district_id": "LK-81",
    "lg_id": "LG-81006",
    "ward_num": 0,
    "party": "UNP",
    "name": "Rathnayaka Mudiyanselage Samanlatha Rathnayaka"
  },
  {
    "district_id": "LK-81",
    "lg_id": "LG-81006",
    "ward_num": 0,
    "party": "UNP",
    "name": "Sadasivam Thilakarani"
  },
  {
    "district_id": "LK-81",
    "lg_id": "LG-81006",
    "ward_num": 0,
    "party": "UNP",
    "name": "Sivakumar Madumitha"
  },
  {
    "district_id": "LK-81",
    "lg_id": "LG-81006",
    "ward_num": 0,
    "party": "UNP",
    "name": "Wijayasingha Mudiyanselage Anura Bandara"
  },
  {
    "district_id": "LK-81",
    "lg_id": "LG-81006",
    "ward_num": 1,
    "party": "CWC(",
    "name": "Mahendran Ranjani"
  },
  {
    "district_id": "LK-81",
    "lg_id": "LG-81006",
    "ward_num": 1,
    "party": "FPF",
    "name": "Thennakoon Mudiyanselage Abeywickrama"
  },
  {
    "district_id": "LK-81",
    "lg_id": "LG-81006",
    "ward_num": 1,
    "party": "IG1",
    "name": "Dissanayaka Mudiyanselage Gunasekara"
  },
  {
    "district_id": "LK-81",
    "lg_id": "LG-81006",
    "ward_num": 1,
    "party": "JJB",
    "name": "T.M.Gayan Gunasinghe"
  },
  {
    "district_id": "LK-81",
    "lg_id": "LG-81006",
    "ward_num": 1,
    "party": "NDF",
    "name": "Rajendran Pathmanadan"
  },
  {
    "district_id": "LK-81",
    "lg_id": "LG-81006",
    "ward_num": 1,
    "party": "SJB",
    "name": "Dissanayaka Mudiyanselage Piyadasa"
  },
  {
    "district_id": "LK-81",
    "lg_id": "LG-81006",
    "ward_num": 1,
    "party": "SLPP",
    "name": "Dissanayaka Mudiyanselage Rohana Kumara Sisira Dissanayaka"
  },
  {
    "district_id": "LK-81",
    "lg_id": "LG-81006",
    "ward_num": 1,
    "party": "UNP",
    "name": "Dissanayaka Mudiyanselage Wijerathna"
  },
  {
    "district_id": "LK-81",
    "lg_id": "LG-81006",
    "ward_num": 2,
    "party": "CWC(",
    "name": "Muththusamy Paranjothi"
  },
  {
    "district_id": "LK-81",
    "lg_id": "LG-81006",
    "ward_num": 2,
    "party": "FPF",
    "name": "Konara Mudiyanselage Kumari Kusumalatha"
  },
  {
    "district_id": "LK-81",
    "lg_id": "LG-81006",
    "ward_num": 2,
    "party": "IG1",
    "name": "Dissanayaka Mudiyanselage Indrawathi"
  },
  {
    "district_id": "LK-81",
    "lg_id": "LG-81006",
    "ward_num": 2,
    "party": "JJB",
    "name": "D.M. Chandrarathna"
  },
  {
    "district_id": "LK-81",
    "lg_id": "LG-81006",
    "ward_num": 2,
    "party": "NDF",
    "name": "Ghanasundaram Vinayagasundaram"
  },
  {
    "district_id": "LK-81",
    "lg_id": "LG-81006",
    "ward_num": 2,
    "party": "SJB",
    "name": "Siwalingam Yogaraj"
  },
  {
    "district_id": "LK-81",
    "lg_id": "LG-81006",
    "ward_num": 2,
    "party": "SLPP",
    "name": "Dissanayaka Mudiyanselage Preethika Priyadarshani"
  },
  {
    "district_id": "LK-81",
    "lg_id": "LG-81006",
    "ward_num": 2,
    "party": "UNP",
    "name": "Mahiwannan Sashan"
  },
  {
    "district_id": "LK-81",
    "lg_id": "LG-81006",
    "ward_num": 3,
    "party": "CWC(",
    "name": "Ramachandran Puwaneshwaran"
  },
  {
    "district_id": "LK-81",
    "lg_id": "LG-81006",
    "ward_num": 3,
    "party": "FPF",
    "name": "Wijesingha Mudiyanselage Thunethrarathna Priyantha"
  },
  {
    "district_id": "LK-81",
    "lg_id": "LG-81006",
    "ward_num": 3,
    "party": "IG1",
    "name": "Wijesingha Mudiyanselage Punchibanda"
  },
  {
    "district_id": "LK-81",
    "lg_id": "LG-81006",
    "ward_num": 3,
    "party": "JJB",
    "name": "R.M. Samantha Rathnayaka"
  },
  {
    "district_id": "LK-81",
    "lg_id": "LG-81006",
    "ward_num": 3,
    "party": "NDF",
    "name": "Muthusami Yogeswaran"
  },
  {
    "district_id": "LK-81",
    "lg_id": "LG-81006",
    "ward_num": 3,
    "party": "SJB",
    "name": "Weerasingha Mudiyanselage Pradeep Bandara Weerasingha"
  },
  {
    "district_id": "LK-81",
    "lg_id": "LG-81006",
    "ward_num": 3,
    "party": "SLPP",
    "name": "Rathnayaka Mudiyanselage Weerathunga"
  },
  {
    "district_id": "LK-81",
    "lg_id": "LG-81006",
    "ward_num": 3,
    "party": "UNP",
    "name": "Murugesu Sulosina"
  },
  {
    "district_id": "LK-81",
    "lg_id": "LG-81006",
    "ward_num": 4,
    "party": "CWC(",
    "name": "Suppaiya Sudhagar"
  },
  {
    "district_id": "LK-81",
    "lg_id": "LG-81006",
    "ward_num": 4,
    "party": "FPF",
    "name": "Dissanayaka Mudiyanselage Leela Chandrani"
  },
  {
    "district_id": "LK-81",
    "lg_id": "LG-81006",
    "ward_num": 4,
    "party": "IG1",
    "name": "Rathnayaka Mudiyanselage Wijerathna"
  },
  {
    "district_id": "LK-81",
    "lg_id": "LG-81006",
    "ward_num": 4,
    "party": "JJB",
    "name": "S. Nawaraj"
  },
  {
    "district_id": "LK-81",
    "lg_id": "LG-81006",
    "ward_num": 4,
    "party": "NDF",
    "name": "Subramaniyam Manimuli"
  },
  {
    "district_id": "LK-81",
    "lg_id": "LG-81006",
    "ward_num": 4,
    "party": "SJB",
    "name": "Eewamparam Sudakaran"
  },
  {
    "district_id": "LK-81",
    "lg_id": "LG-81006",
    "ward_num": 4,
    "party": "SLPP",
    "name": "Samarakoon Mudiyanselage Ajith Chandrakumara de Samarakoon"
  },
  {
    "district_id": "LK-81",
    "lg_id": "LG-81006",
    "ward_num": 4,
    "party": "UNP",
    "name": "Samarakoon Mudiyanselage Susantha Siri Samarakon"
  },
  {
    "district_id": "LK-81",
    "lg_id": "LG-81006",
    "ward_num": 5,
    "party": "CWC(",
    "name": "Veloo Ravi"
  },
  {
    "district_id": "LK-81",
    "lg_id": "LG-81006",
    "ward_num": 5,
    "party": "FPF",
    "name": "Bastiyan Dhanushka Sampath Fernando"
  },
  {
    "district_id": "LK-81",
    "lg_id": "LG-81006",
    "ward_num": 5,
    "party": "IG1",
    "name": "Kumarage Don Sarath Abeypala"
  },
  {
    "district_id": "LK-81",
    "lg_id": "LG-81006",
    "ward_num": 5,
    "party": "JJB",
    "name": "R.M. Kusum Kumar Chaminda Rathnayaka"
  },
  {
    "district_id": "LK-81",
    "lg_id": "LG-81006",
    "ward_num": 5,
    "party": "NDF",
    "name": "Sawarimuththu Cristopol"
  },
  {
    "district_id": "LK-81",
    "lg_id": "LG-81006",
    "ward_num": 5,
    "party": "SJB",
    "name": "Arumugam Sadiskumar"
  },
  {
    "district_id": "LK-81",
    "lg_id": "LG-81006",
    "ward_num": 5,
    "party": "SLPP",
    "name": "Rajapaksha Waththe Widanelage Ghanawathi"
  },
  {
    "district_id": "LK-81",
    "lg_id": "LG-81006",
    "ward_num": 5,
    "party": "UNP",
    "name": "Wickramasingha Mudiyanselage Shanika Dilani"
  },
  {
    "district_id": "LK-81",
    "lg_id": "LG-81006",
    "ward_num": 6,
    "party": "CWC(",
    "name": "Sangaralingam Satheeshkumar"
  },
  {
    "district_id": "LK-81",
    "lg_id": "LG-81006",
    "ward_num": 6,
    "party": "CWC(",
    "name": "Sapramaniam Pusparani"
  },
  {
    "district_id": "LK-81",
    "lg_id": "LG-81006",
    "ward_num": 6,
    "party": "FPF",
    "name": "Dissanayaka Mudiyanselage Sudunilame"
  },
  {
    "district_id": "LK-81",
    "lg_id": "LG-81006",
    "ward_num": 6,
    "party": "FPF",
    "name": "Rajarathna Wickramasingha Mudiyanselage Rathnayaka"
  },
  {
    "district_id": "LK-81",
    "lg_id": "LG-81006",
    "ward_num": 6,
    "party": "IG1",
    "name": "Najamudin Mohomad Anwar"
  },
  {
    "district_id": "LK-81",
    "lg_id": "LG-81006",
    "ward_num": 6,
    "party": "IG1",
    "name": "Senarath Bandula Wijesingha"
  },
  {
    "district_id": "LK-81",
    "lg_id": "LG-81006",
    "ward_num": 6,
    "party": "JJB",
    "name": "K. Sunil Santha"
  },
  {
    "district_id": "LK-81",
    "lg_id": "LG-81006",
    "ward_num": 6,
    "party": "JJB",
    "name": "M. Nilmini Udeshika Damayanthi"
  },
  {
    "district_id": "LK-81",
    "lg_id": "LG-81006",
    "ward_num": 6,
    "party": "NDF",
    "name": "Ghanaselwam Samila"
  },
  {
    "district_id": "LK-81",
    "lg_id": "LG-81006",
    "ward_num": 6,
    "party": "NDF",
    "name": "Karupayya Wivekanda Raja"
  },
  {
    "district_id": "LK-81",
    "lg_id": "LG-81006",
    "ward_num": 6,
    "party": "SJB",
    "name": "Hettiwannaku Nawarathna Bandara Rajapakasha Mudiyanselage Rukman Gamini Rajapaksha"
  },
  {
    "district_id": "LK-81",
    "lg_id": "LG-81006",
    "ward_num": 6,
    "party": "SJB",
    "name": "Mohomad Aliyar Musammil"
  },
  {
    "district_id": "LK-81",
    "lg_id": "LG-81006",
    "ward_num": 6,
    "party": "SLPP",
    "name": "Beligahagedara Peterlage Anula de Silva"
  },
  {
    "district_id": "LK-81",
    "lg_id": "LG-81006",
    "ward_num": 6,
    "party": "SLPP",
    "name": "Wanni Arachchige Nimal Jayasingha"
  },
  {
    "district_id": "LK-81",
    "lg_id": "LG-81006",
    "ward_num": 6,
    "party": "UNP",
    "name": "Sivalingam Pathmanadan"
  },
  {
    "district_id": "LK-81",
    "lg_id": "LG-81006",
    "ward_num": 6,
    "party": "UNP",
    "name": "Themapana Mesthriyage Kasun Dhananjaya Ariyasena"
  },
  {
    "district_id": "LK-81",
    "lg_id": "LG-81006",
    "ward_num": 7,
    "party": "CWC(",
    "name": "Kalimuthu Mahadevan"
  },
  {
    "district_id": "LK-81",
    "lg_id": "LG-81006",
    "ward_num": 7,
    "party": "FPF",
    "name": "Dissanayaka Mudiyanselage Ashoka Lasantha"
  },
  {
    "district_id": "LK-81",
    "lg_id": "LG-81006",
    "ward_num": 7,
    "party": "IG1",
    "name": "Jayasooriya Arachchilage Dona Manjari Shanika Jayasooriya"
  },
  {
    "district_id": "LK-81",
    "lg_id": "LG-81006",
    "ward_num": 7,
    "party": "JJB",
    "name": "M.P. Jayathunga"
  },
  {
    "district_id": "LK-81",
    "lg_id": "LG-81006",
    "ward_num": 7,
    "party": "NDF",
    "name": "Palaniyandi Ramakrishnan"
  },
  {
    "district_id": "LK-81",
    "lg_id": "LG-81006",
    "ward_num": 7,
    "party": "SJB",
    "name": "Hewaponsekage Susantha Ponseka"
  },
  {
    "district_id": "LK-81",
    "lg_id": "LG-81006",
    "ward_num": 7,
    "party": "SLPP",
    "name": "Katupulle Mudiyanselage Wijerathna"
  },
  {
    "district_id": "LK-81",
    "lg_id": "LG-81006",
    "ward_num": 7,
    "party": "UNP",
    "name": "Peramaiya Sivakumar"
  },
  {
    "district_id": "LK-81",
    "lg_id": "LG-81006",
    "ward_num": 8,
    "party": "CWC(",
    "name": "Ramanathan Chandragasan"
  },
  {
    "district_id": "LK-81",
    "lg_id": "LG-81006",
    "ward_num": 8,
    "party": "FPF",
    "name": "Kirulapana Mohotti Arachchilage Meril Henasly Almeda"
  },
  {
    "district_id": "LK-81",
    "lg_id": "LG-81006",
    "ward_num": 8,
    "party": "IG1",
    "name": "Rajapaksha Mudiyanselage Predeep Kumara"
  },
  {
    "district_id": "LK-81",
    "lg_id": "LG-81006",
    "ward_num": 8,
    "party": "JJB",
    "name": "D. Sridaran"
  },
  {
    "district_id": "LK-81",
    "lg_id": "LG-81006",
    "ward_num": 8,
    "party": "NDF",
    "name": "Perumal Krisnakumar"
  },
  {
    "district_id": "LK-81",
    "lg_id": "LG-81006",
    "ward_num": 8,
    "party": "SJB",
    "name": "Mohidin Abdul Kadar"
  },
  {
    "district_id": "LK-81",
    "lg_id": "LG-81006",
    "ward_num": 8,
    "party": "SLPP",
    "name": "Wanasingha Mudiyanselage Irangani"
  },
  {
    "district_id": "LK-81",
    "lg_id": "LG-81006",
    "ward_num": 8,
    "party": "UNP",
    "name": "Sivasami Sinnathambi Manoharan"
  },
  {
    "district_id": "LK-81",
    "lg_id": "LG-81006",
    "ward_num": 9,
    "party": "CWC(",
    "name": "Sivalingam Vijayan"
  },
  {
    "district_id": "LK-81",
    "lg_id": "LG-81006",
    "ward_num": 9,
    "party": "FPF",
    "name": "Wanasingha Mudiyanselage Sunil Gunawardhana"
  },
  {
    "district_id": "LK-81",
    "lg_id": "LG-81006",
    "ward_num": 9,
    "party": "IG1",
    "name": "Wanasingha Mudiyanselage Ajith Preethi Kumara Jayasundara"
  },
  {
    "district_id": "LK-81",
    "lg_id": "LG-81006",
    "ward_num": 9,
    "party": "JJB",
    "name": "W.M. Jayasena"
  },
  {
    "district_id": "LK-81",
    "lg_id": "LG-81006",
    "ward_num": 9,
    "party": "NDF",
    "name": "Josep Burunam Hendriboos"
  },
  {
    "district_id": "LK-81",
    "lg_id": "LG-81006",
    "ward_num": 9,
    "party": "SJB",
    "name": "Jeyanthiran Nishandani"
  },
  {
    "district_id": "LK-81",
    "lg_id": "LG-81006",
    "ward_num": 9,
    "party": "SLPP",
    "name": "Thamilwanam Vimalraji"
  },
  {
    "district_id": "LK-81",
    "lg_id": "LG-81006",
    "ward_num": 9,
    "party": "UNP",
    "name": "Vishwanadan Neris Kumar"
  },
  {
    "district_id": "LK-81",
    "lg_id": "LG-81006",
    "ward_num": 10,
    "party": "CWC(",
    "name": "Kanagaraja Logeshwaram"
  },
  {
    "district_id": "LK-81",
    "lg_id": "LG-81006",
    "ward_num": 10,
    "party": "FPF",
    "name": "Rathnayaka Mudiyanselage Anura"
  },
  {
    "district_id": "LK-81",
    "lg_id": "LG-81006",
    "ward_num": 10,
    "party": "IG1",
    "name": "Jayasingha Mudiyanselage Dushantha Pushpa Kumara"
  },
  {
    "district_id": "LK-81",
    "lg_id": "LG-81006",
    "ward_num": 10,
    "party": "JJB",
    "name": "K.M. Sarana Nandana Bandara"
  },
  {
    "district_id": "LK-81",
    "lg_id": "LG-81006",
    "ward_num": 10,
    "party": "NDF",
    "name": "Subramaniyam Winayagarmurthi"
  },
  {
    "district_id": "LK-81",
    "lg_id": "LG-81006",
    "ward_num": 10,
    "party": "SJB",
    "name": "Thuwan Ansar Farid"
  },
  {
    "district_id": "LK-81",
    "lg_id": "LG-81006",
    "ward_num": 10,
    "party": "SLPP",
    "name": "Handunneththi Kokila Idunil Chameera Mendis"
  },
  {
    "district_id": "LK-81",
    "lg_id": "LG-81006",
    "ward_num": 10,
    "party": "UNP",
    "name": "Welu Thangaraj"
  },
  {
    "district_id": "LK-81",
    "lg_id": "LG-81006",
    "ward_num": 11,
    "party": "CWC(",
    "name": "Nayagam Niekalas"
  },
  {
    "district_id": "LK-81",
    "lg_id": "LG-81006",
    "ward_num": 11,
    "party": "FPF",
    "name": "Paththinige Asanka Dewapriya Paththinige"
  },
  {
    "district_id": "LK-81",
    "lg_id": "LG-81006",
    "ward_num": 11,
    "party": "IG1",
    "name": "Senevirathna Arachchilage Sepala"
  },
  {
    "district_id": "LK-81",
    "lg_id": "LG-81006",
    "ward_num": 11,
    "party": "JJB",
    "name": "A.M. Samanthi"
  },
  {
    "district_id": "LK-81",
    "lg_id": "LG-81006",
    "ward_num": 11,
    "party": "NDF",
    "name": "Ambikapathi Chandrasegar"
  },
  {
    "district_id": "LK-81",
    "lg_id": "LG-81006",
    "ward_num": 11,
    "party": "SJB",
    "name": "Karupayya Nirmaladevi"
  },
  {
    "district_id": "LK-81",
    "lg_id": "LG-81006",
    "ward_num": 11,
    "party": "SLPP",
    "name": "Konara Mudiyanselage Somapala"
  },
  {
    "district_id": "LK-81",
    "lg_id": "LG-81006",
    "ward_num": 11,
    "party": "UNP",
    "name": "Kalu Arachchige Don Nihal Premasiri"
  },
  {
    "district_id": "LK-81",
    "lg_id": "LG-81006",
    "ward_num": 12,
    "party": "CWC(",
    "name": "Samiraj Krishnaraj"
  },
  {
    "district_id": "LK-81",
    "lg_id": "LG-81006",
    "ward_num": 12,
    "party": "FPF",
    "name": "Rateralalage Janaka Chandrathilaka"
  },
  {
    "district_id": "LK-81",
    "lg_id": "LG-81006",
    "ward_num": 12,
    "party": "IG1",
    "name": "Mapa Mudiyanselage Nilanga Ruwan Kumara"
  },
  {
    "district_id": "LK-81",
    "lg_id": "LG-81006",
    "ward_num": 12,
    "party": "JJB",
    "name": "H.M. Jayasekara"
  },
  {
    "district_id": "LK-81",
    "lg_id": "LG-81006",
    "ward_num": 12,
    "party": "NDF",
    "name": "Narayanasami Sasikumar"
  },
  {
    "district_id": "LK-81",
    "lg_id": "LG-81006",
    "ward_num": 12,
    "party": "SJB",
    "name": "Sukirtha Nandam Karthiswaran"
  },
  {
    "district_id": "LK-81",
    "lg_id": "LG-81006",
    "ward_num": 12,
    "party": "SLPP",
    "name": "Gunamuni Gayathra Madurangi Mandis"
  },
  {
    "district_id": "LK-81",
    "lg_id": "LG-81006",
    "ward_num": 12,
    "party": "UNP",
    "name": "Weerasami Rajendran"
  }
]