[
  {
    "lg_id": "LG-43003",
    "lg_name": "Vavuniya South (Tamil) PS",
    "n_members": "1",
    "ward_name": "Maradamadu",
    "ward_num": "1"
  },
  {
    "lg_id": "LG-43003",
    "lg_name": "Vavuniya South (Tamil) PS",
    "n_members": "2",
    "ward_name": "Nelukkulam",
    "ward_num": "10"
  },
  {
    "lg_id": "LG-43003",
    "lg_name": "Vavuniya South (Tamil) PS",
    "n_members": "2",
    "ward_name": "Kandapuram",
    "ward_num": "11"
  },
  {
    "lg_id": "LG-43003",
    "lg_name": "Vavuniya South (Tamil) PS",
    "n_members": "1",
    "ward_name": "Samankulam",
    "ward_num": "12"
  },
  {
    "lg_id": "LG-43003",
    "lg_name": "Vavuniya South (Tamil) PS",
    "n_members": "1",
    "ward_name": "Asikulam",
    "ward_num": "13"
  },
  {
    "lg_id": "LG-43003",
    "lg_name": "Vavuniya South (Tamil) PS",
    "n_members": "1",
    "ward_name": "Semamadu",
    "ward_num": "2"
  },
  {
    "lg_id": "LG-43003",
    "lg_name": "Vavuniya South (Tamil) PS",
    "n_members": "1",
    "ward_name": "Ichchankulam",
    "ward_num": "3"
  },
  {
    "lg_id": "LG-43003",
    "lg_name": "Vavuniya South (Tamil) PS",
    "n_members": "1",
    "ward_name": "Sasthrikulamkulam",
    "ward_num": "4"
  },
  {
    "lg_id": "LG-43003",
    "lg_name": "Vavuniya South (Tamil) PS",
    "n_members": "1",
    "ward_name": "Poowarasankulam",
    "ward_num": "5"
  },
  {
    "lg_id": "LG-43003",
    "lg_name": "Vavuniya South (Tamil) PS",
    "n_members": "2",
    "ward_name": "Salambeikulam",
    "ward_num": "6"
  },
  {
    "lg_id": "LG-43003",
    "lg_name": "Vavuniya South (Tamil) PS",
    "n_members": "1",
    "ward_name": "Pampaimadu",
    "ward_num": "7"
  },
  {
    "lg_id": "LG-43003",
    "lg_name": "Vavuniya South (Tamil) PS",
    "n_members": "1",
    "ward_name": "Marakkaranpalai",
    "ward_num": "8"
  },
  {
    "lg_id": "LG-43003",
    "lg_name": "Vavuniya South (Tamil) PS",
    "n_members": "1",
    "ward_name": "Maharambeikulam",
    "ward_num": "9"
  }
]